aimlLabPrograms/__init__.py
aimlLabPrograms/programs.py
aimlLabPrograms-1.0.1.dist-info/LICENSE
aimlLabPrograms-1.0.1.dist-info/METADATA
aimlLabPrograms-1.0.1.dist-info/WHEEL
aimlLabPrograms-1.0.1.dist-info/top_level.txt
aimlLabPrograms-1.0.1.dist-info/RECORD
