Metadata-Version: 2.1
Name: aimlLabPrograms
Version: 1.0.1
Summary: A package containing Python programs for AI and ML lab exercises
Author: Harry Potter
Author-email: wizardingworld474@example.com
License: MIT
Classifier: Programming Language :: Python :: 3
Classifier: License :: OSI Approved :: MIT License
Classifier: Operating System :: OS Independent
Requires-Python: >=3.6
License-File: LICENSE
